flask2postman.py
flask2postman-1.4.4.dist-info/LICENSE
flask2postman-1.4.4.dist-info/METADATA
flask2postman-1.4.4.dist-info/WHEEL
flask2postman-1.4.4.dist-info/entry_points.txt
flask2postman-1.4.4.dist-info/top_level.txt
flask2postman-1.4.4.dist-info/RECORD
